gobjectservicelib/__init__.py
gobjectservicelib/eventloop.py
gobjectservicelib/py.typed
gobjectservicelib/service.py
gobjectservicelib/widgets.py
gobjectservicelib-1.4.1.dist-info/LICENSE
gobjectservicelib-1.4.1.dist-info/WHEEL
gobjectservicelib-1.4.1.dist-info/METADATA
gobjectservicelib-1.4.1.dist-info/RECORD
