Metadata-Version: 2.1
Name: gobjectservicelib
Version: 1.4.1
Summary: GObject mainloop implementation of https://gitlab.com/advian-oss/python-datastreamservicelib
Home-page: https://gitlab.com/advian-oss/python-gobjectservicelib/
License: MIT
Author: Eero af Heurlin
Author-email: eero.afheurlin@advian.fi
Requires-Python: >=3.6.2,<4.0
Classifier: License :: OSI Approved :: MIT License
Classifier: Programming Language :: Python :: 3
Classifier: Programming Language :: Python :: 3.10
Classifier: Programming Language :: Python :: 3.7
Classifier: Programming Language :: Python :: 3.8
Classifier: Programming Language :: Python :: 3.9
Requires-Dist: PyGObject (>=3.42,<4.0)
Requires-Dist: datastreamservicelib (>=1.12,<2.0)
Project-URL: Repository, https://gitlab.com/advian-oss/python-gobjectservicelib/
